{
  "trainNumber": "39",
  "trainType": {
    "id": 7,
    "name": {
      "en": "Improved",
      "ar": "محسن"
    },
    "description": {
      "en": "Enhanced trains with modern technology and updated comfort features",
      "ar": "قطارات محسنة بتقنيات حديثة ووسائل راحة محدثة"
    }
  },
  "route": {
    "from": {
      "stationId": "4",
      "name": {
        "en": "Tanta",
        "ar": "طنطا"
      }
    },
    "to": {
      "stationId": "10",
      "name": {
        "en": "Mansoura",
        "ar": "المنصورة"
      }
    }
  },
  "schedule": {
    "startTime": "22:10",
    "endTime": "23:40",
    "stations": [
      {
        "stationId": 4,
        "stationName": {
          "en": "Tanta",
          "ar": "طنطا"
        },
        "arrivalTime": null,
        "departureTime": "22:10"
      },
      {
        "stationId": 570,
        "stationName": {
          "en": "Ragdiah",
          "ar": "الرجدية"
        },
        "arrivalTime": "22:18",
        "departureTime": "22:19"
      },
      {
        "stationId": 571,
        "stationName": {
          "en": "Shebshir Hessah",
          "ar": "شبشير الحصة"
        },
        "arrivalTime": "22:25",
        "departureTime": "22:26"
      },
      {
        "stationId": 572,
        "stationName": {
          "en": "Mahallat Rouh",
          "ar": "محلة روح"
        },
        "arrivalTime": "22:30",
        "departureTime": "22:31"
      },
      {
        "stationId": 573,
        "stationName": {
          "en": "Saft Turab",
          "ar": "صفط تراب"
        },
        "arrivalTime": "22:37",
        "departureTime": "22:38"
      },
      {
        "stationId": 574,
        "stationName": {
          "en": "Minyat Shentena Ayash",
          "ar": "منية شنتا عياش"
        },
        "arrivalTime": "22:43",
        "departureTime": "22:44"
      },
      {
        "stationId": 575,
        "stationName": {
          "en": "Manshyt Bakry",
          "ar": "منشية البكري"
        },
        "arrivalTime": "22:47",
        "departureTime": "22:48"
      },
      {
        "stationId": 576,
        "stationName": {
          "en": "Mahalla Kubra",
          "ar": "المحلة الكبرى"
        },
        "arrivalTime": "22:51",
        "departureTime": "22:52"
      },
      {
        "stationId": 577,
        "stationName": {
          "en": "Ghazl Mahalla",
          "ar": "غزل المحلة"
        },
        "arrivalTime": "22:54",
        "departureTime": "22:55"
      },
      {
        "stationId": 578,
        "stationName": {
          "en": "Mahallat Abo Ali Qantara",
          "ar": "محلة ابو على القنطرة"
        },
        "arrivalTime": "22:57",
        "departureTime": "22:58"
      },
      {
        "stationId": 579,
        "stationName": {
          "en": "Rahbayn",
          "ar": "الراهبين"
        },
        "arrivalTime": "23:01",
        "departureTime": "23:02"
      },
      {
        "stationId": 580,
        "stationName": {
          "en": "Samannoud",
          "ar": "سمنود"
        },
        "arrivalTime": "23:06",
        "departureTime": "23:07"
      },
      {
        "stationId": 581,
        "stationName": {
          "en": "Mit Khalaf",
          "ar": "ميت خلف"
        },
        "arrivalTime": "23:13",
        "departureTime": "23:14"
      },
      {
        "stationId": 582,
        "stationName": {
          "en": "Mit Assas",
          "ar": "ميت عساس"
        },
        "arrivalTime": "23:18",
        "departureTime": "23:19"
      },
      {
        "stationId": 583,
        "stationName": {
          "en": "Kafr Arab",
          "ar": "كفر العرب"
        },
        "arrivalTime": "23:23",
        "departureTime": "23:24"
      },
      {
        "stationId": 674,
        "stationName": {
          "en": "Mit Korma",
          "ar": "ميت الكرما"
        },
        "arrivalTime": "23:28",
        "departureTime": "23:29"
      },
      {
        "stationId": 584,
        "stationName": {
          "en": "Talkha",
          "ar": "طلخا"
        },
        "arrivalTime": "23:35",
        "departureTime": "23:36"
      },
      {
        "stationId": 10,
        "stationName": {
          "en": "Mansoura",
          "ar": "المنصورة"
        },
        "arrivalTime": "23:40",
        "departureTime": null
      }
    ],
    "totalStations": 18
  },
  "status": {
    "working": "This is a Test String :)",
    "lastUpdate": "01/09/2023"
  },
  "notes": {
    "en": null,
    "ar": null
  }
}