{
  "trainNumber": "557",
  "trainType": {
    "id": 7,
    "name": {
      "en": "Improved",
      "ar": "محسن"
    },
    "description": {
      "en": "Enhanced trains with modern technology and updated comfort features",
      "ar": "قطارات محسنة بتقنيات حديثة ووسائل راحة محدثة"
    }
  },
  "route": {
    "from": {
      "stationId": "0",
      "name": {
        "en": "Cairo",
        "ar": "القاهرة"
      }
    },
    "to": {
      "stationId": "28",
      "name": {
        "en": "Kafr Zayat",
        "ar": "كفر الزيات"
      }
    }
  },
  "schedule": {
    "startTime": "18:40",
    "endTime": "22:45",
    "stations": [
      {
        "stationId": 0,
        "stationName": {
          "en": "Cairo",
          "ar": "القاهرة"
        },
        "arrivalTime": null,
        "departureTime": "18:40"
      },
      {
        "stationId": 38,
        "stationName": {
          "en": "Shobra Khemah",
          "ar": "شبرا الخيمة"
        },
        "arrivalTime": "18:54",
        "departureTime": "18:56"
      },
      {
        "stationId": 36,
        "stationName": {
          "en": "Qalyoub",
          "ar": "قليوب"
        },
        "arrivalTime": "19:06",
        "departureTime": "19:09"
      },
      {
        "stationId": 631,
        "stationName": {
          "en": "Qalyoub B",
          "ar": "قليوب البلد"
        },
        "arrivalTime": "19:13",
        "departureTime": "19:17"
      },
      {
        "stationId": 630,
        "stationName": {
          "en": "Shalaqan",
          "ar": "شلقان"
        },
        "arrivalTime": "19:21",
        "departureTime": "19:22"
      },
      {
        "stationId": 629,
        "stationName": {
          "en": "Qanatir N",
          "ar": "القناطر ج"
        },
        "arrivalTime": "19:27",
        "departureTime": "19:28"
      },
      {
        "stationId": 628,
        "stationName": {
          "en": "Derwah",
          "ar": "دروة"
        },
        "arrivalTime": "19:37",
        "departureTime": "19:42"
      },
      {
        "stationId": 627,
        "stationName": {
          "en": "Kafr Sarawah",
          "ar": "كفر صراوة"
        },
        "arrivalTime": "19:45",
        "departureTime": "19:46"
      },
      {
        "stationId": 626,
        "stationName": {
          "en": "Shatanof",
          "ar": "شطانوف"
        },
        "arrivalTime": "19:49",
        "departureTime": "19:50"
      },
      {
        "stationId": 625,
        "stationName": {
          "en": "Hilwasi B",
          "ar": "الحلواصي البلد"
        },
        "arrivalTime": "19:53",
        "departureTime": "19:54"
      },
      {
        "stationId": 624,
        "stationName": {
          "en": "Hilwasi",
          "ar": "الحلواصي"
        },
        "arrivalTime": "19:57",
        "departureTime": "19:58"
      },
      {
        "stationId": 623,
        "stationName": {
          "en": "Mahallat Subk",
          "ar": "محلة سبك"
        },
        "arrivalTime": "20:02",
        "departureTime": "20:03"
      },
      {
        "stationId": 622,
        "stationName": {
          "en": "Ashmun",
          "ar": "اشمون"
        },
        "arrivalTime": "20:10",
        "departureTime": "20:11"
      },
      {
        "stationId": 621,
        "stationName": {
          "en": "Samadun",
          "ar": "سمادون"
        },
        "arrivalTime": "20:16",
        "departureTime": "20:17"
      },
      {
        "stationId": 620,
        "stationName": {
          "en": "Badr Mosque",
          "ar": "جامع بدر"
        },
        "arrivalTime": "20:22",
        "departureTime": "20:23"
      },
      {
        "stationId": 619,
        "stationName": {
          "en": "Ramlat Injib",
          "ar": "رملة الأنجب"
        },
        "arrivalTime": "20:25",
        "departureTime": "20:26"
      },
      {
        "stationId": 618,
        "stationName": {
          "en": "Shama",
          "ar": "شما"
        },
        "arrivalTime": "20:30",
        "departureTime": "20:31"
      },
      {
        "stationId": 617,
        "stationName": {
          "en": "Kamshush",
          "ar": "كمشوش"
        },
        "arrivalTime": "20:35",
        "departureTime": "20:41"
      },
      {
        "stationId": 616,
        "stationName": {
          "en": "Kafr Sanabisah",
          "ar": "كفر السنابسة"
        },
        "arrivalTime": "20:45",
        "departureTime": "20:46"
      },
      {
        "stationId": 615,
        "stationName": {
          "en": "Minuf",
          "ar": "منوف"
        },
        "arrivalTime": "20:50",
        "departureTime": "21:00"
      },
      {
        "stationId": 673,
        "stationName": {
          "en": "Sengerg",
          "ar": "سنجرج"
        },
        "arrivalTime": "21:17",
        "departureTime": "21:18"
      },
      {
        "stationId": 672,
        "stationName": {
          "en": "Monshaat Sultan",
          "ar": "منشأة سلطان"
        },
        "arrivalTime": "21:29",
        "departureTime": "21:30"
      },
      {
        "stationId": 671,
        "stationName": {
          "en": "Iraqiyyah",
          "ar": "العراقية"
        },
        "arrivalTime": "21:34",
        "departureTime": "21:35"
      },
      {
        "stationId": 670,
        "stationName": {
          "en": "Ashma",
          "ar": "عشما"
        },
        "arrivalTime": "21:38",
        "departureTime": "21:39"
      },
      {
        "stationId": 669,
        "stationName": {
          "en": "Shohada",
          "ar": "الشهداء"
        },
        "arrivalTime": "21:42",
        "departureTime": "21:43"
      },
      {
        "stationId": 668,
        "stationName": {
          "en": "Dinshaway",
          "ar": "دنشواى"
        },
        "arrivalTime": "21:49",
        "departureTime": "21:50"
      },
      {
        "stationId": 667,
        "stationName": {
          "en": "Zawiyat Baqli",
          "ar": "زاوية البقلى"
        },
        "arrivalTime": "21:58",
        "departureTime": "21:59"
      },
      {
        "stationId": 666,
        "stationName": {
          "en": "Beshtami",
          "ar": "بشتامي"
        },
        "arrivalTime": "22:02",
        "departureTime": "22:03"
      },
      {
        "stationId": 665,
        "stationName": {
          "en": "Amrus",
          "ar": "عمروس"
        },
        "arrivalTime": "22:07",
        "departureTime": "22:08"
      },
      {
        "stationId": 664,
        "stationName": {
          "en": "Kom Mazin",
          "ar": "كوم مازن"
        },
        "arrivalTime": "22:11",
        "departureTime": "22:12"
      },
      {
        "stationId": 663,
        "stationName": {
          "en": "Tunub",
          "ar": "طنوب"
        },
        "arrivalTime": "22:15",
        "departureTime": "22:16"
      },
      {
        "stationId": 662,
        "stationName": {
          "en": "Izbat Hutaym",
          "ar": "عزبة الحطيم"
        },
        "arrivalTime": "22:20",
        "departureTime": "22:21"
      },
      {
        "stationId": 661,
        "stationName": {
          "en": "Mishlah",
          "ar": "مشلة"
        },
        "arrivalTime": "22:28",
        "departureTime": "22:29"
      },
      {
        "stationId": 660,
        "stationName": {
          "en": "Kafr Mishlah",
          "ar": "كفر مشلة"
        },
        "arrivalTime": "22:31",
        "departureTime": "22:32"
      },
      {
        "stationId": 659,
        "stationName": {
          "en": "Qasr Nasr Din",
          "ar": "قصر نصر الدين"
        },
        "arrivalTime": "22:36",
        "departureTime": "22:37"
      },
      {
        "stationId": 658,
        "stationName": {
          "en": "Daljamun",
          "ar": "الدلجمون"
        },
        "arrivalTime": "22:40",
        "departureTime": "22:41"
      },
      {
        "stationId": 28,
        "stationName": {
          "en": "Kafr Zayat",
          "ar": "كفر الزيات"
        },
        "arrivalTime": "22:45",
        "departureTime": null
      }
    ],
    "totalStations": 37
  },
  "status": {
    "working": "tanta-minuf-cairo (4)",
    "lastUpdate": "26/11/2023"
  },
  "notes": {
    "en": null,
    "ar": null
  }
}