{
  "trainNumber": "2024",
  "trainType": {
    "id": 0,
    "name": {
      "en": "Talgo",
      "ar": "تالجو"
    },
    "description": {
      "en": "Modern high-speed Talgo trains with advanced comfort features",
      "ar": "قطارات تالجو الحديثة عالية السرعة مع وسائل راحة متقدمة"
    }
  },
  "route": {
    "from": {
      "stationId": "1",
      "name": {
        "en": "Alexandria",
        "ar": "الاسكندرية"
      }
    },
    "to": {
      "stationId": "0",
      "name": {
        "en": "Cairo",
        "ar": "القاهرة"
      }
    }
  },
  "schedule": {
    "startTime": "14:00",
    "endTime": "16:30",
    "stations": [
      {
        "stationId": 1,
        "stationName": {
          "en": "Alexandria",
          "ar": "الاسكندرية"
        },
        "arrivalTime": null,
        "departureTime": "14:00"
      },
      {
        "stationId": 2,
        "stationName": {
          "en": "Sidi Gaber",
          "ar": "سيدي جابر"
        },
        "arrivalTime": "14:12",
        "departureTime": "14:17"
      },
      {
        "stationId": 0,
        "stationName": {
          "en": "Cairo",
          "ar": "القاهرة"
        },
        "arrivalTime": "16:30",
        "departureTime": null
      }
    ],
    "totalStations": 3
  },
  "status": {
    "working": "This is a Test String :)",
    "lastUpdate": "20/08/2023"
  },
  "notes": {
    "en": null,
    "ar": null
  }
}