{
  "trainNumber": "937",
  "trainType": {
    "id": 2,
    "name": {
      "en": "VIP",
      "ar": "خاص"
    },
    "description": {
      "en": "Luxury VIP trains with premium services and exceptional comfort",
      "ar": "قطارات خاصة فاخرة بخدمات مميزة وراحة استثنائية"
    }
  },
  "route": {
    "from": {
      "stationId": "16",
      "name": {
        "en": "Minya",
        "ar": "المنيا"
      }
    },
    "to": {
      "stationId": "0",
      "name": {
        "en": "Cairo",
        "ar": "القاهرة"
      }
    }
  },
  "schedule": {
    "startTime": "14:00",
    "endTime": "17:30",
    "stations": [
      {
        "stationId": 16,
        "stationName": {
          "en": "Minya",
          "ar": "المنيا"
        },
        "arrivalTime": null,
        "departureTime": "14:00"
      },
      {
        "stationId": 80,
        "stationName": {
          "en": "Maghagha",
          "ar": "مغاغة"
        },
        "arrivalTime": "14:49",
        "departureTime": "14:50"
      },
      {
        "stationId": 15,
        "stationName": {
          "en": "Beni Suef",
          "ar": "بني سويف"
        },
        "arrivalTime": "15:34",
        "departureTime": "15:35"
      },
      {
        "stationId": 62,
        "stationName": {
          "en": "Wasta",
          "ar": "الواسطى"
        },
        "arrivalTime": "16:01",
        "departureTime": "16:02"
      },
      {
        "stationId": 13,
        "stationName": {
          "en": "Giza",
          "ar": "الجيزة"
        },
        "arrivalTime": "17:09",
        "departureTime": "17:10"
      },
      {
        "stationId": 12,
        "stationName": {
          "en": "Upper Egypt",
          "ar": "صعيد مصر"
        },
        "arrivalTime": "17:21",
        "departureTime": "17:22"
      },
      {
        "stationId": 0,
        "stationName": {
          "en": "Cairo",
          "ar": "القاهرة"
        },
        "arrivalTime": "17:30",
        "departureTime": null
      }
    ],
    "totalStations": 7
  },
  "status": {
    "working": "This is a Test String :)",
    "lastUpdate": "28/10/2024"
  },
  "notes": {
    "en": null,
    "ar": null
  }
}